setup.py
phasetumblr/__init__.py
phasetumblr/phasetumblr.py
phasetumblr/settings.py
phasetumblr.egg-info/PKG-INFO
phasetumblr.egg-info/SOURCES.txt
phasetumblr.egg-info/dependency_links.txt
phasetumblr.egg-info/not-zip-safe
phasetumblr.egg-info/requires.txt
phasetumblr.egg-info/top_level.txt