Metadata-Version: 1.0
Name: phasetumblr
Version: 0.1
Summary: All the posts from a tumblr blog in a python list. 
Home-page: http://github.com/phasemix/phasetumblr
Author: Roberto Allende
Author-email: rallende@gmail.com
License: Apache 2.0
Platform: UNKNOWN
